jsonmgnt/__init__.py
jsonmgnt/lexer.py
jsonmgnt/parser.py
jsonmgnt-1.1.1.dist-info/LICENSE
jsonmgnt-1.1.1.dist-info/METADATA
jsonmgnt-1.1.1.dist-info/WHEEL
jsonmgnt-1.1.1.dist-info/top_level.txt
jsonmgnt-1.1.1.dist-info/RECORD
