Metadata-Version: 2.1
Name: jsonmgnt
Version: 1.1.1
Summary: A JSON parser written in Python.
Home-page: https://github.com/mariereidj001/jsonmgnt
Author: Marie Reid
Author-email: mariereidj0019291@gmail.com
License: MIT
Classifier: License :: OSI Approved :: MIT License
Classifier: Operating System :: OS Independent
Classifier: Programming Language :: Python :: 3
Classifier: Programming Language :: Python :: 3 :: Only
Classifier: Programming Language :: Python :: 3.6
Classifier: Programming Language :: Python :: 3.7
Classifier: Programming Language :: Python :: 3.8
Classifier: Programming Language :: Python :: 3.9
Requires-Python: >=3.6
License-File: LICENSE
Provides-Extra: dev
Requires-Dist: pytest >=6.2.2 ; extra == 'dev'
